webexteamsbot/__init__.py
webexteamsbot/models.py
webexteamsbot/webexteamsbot.py
webexteamsbot-0.1.4.2.dist-info/AUTHORS.rst
webexteamsbot-0.1.4.2.dist-info/LICENSE
webexteamsbot-0.1.4.2.dist-info/METADATA
webexteamsbot-0.1.4.2.dist-info/WHEEL
webexteamsbot-0.1.4.2.dist-info/top_level.txt
webexteamsbot-0.1.4.2.dist-info/RECORD
