Metadata-Version: 2.1
Name: webexteamsbot
Version: 0.1.4.2
Summary: A Flask based Webex Teams chat bot.
Home-page: https://github.com/hpreston/webexteamsbot
Author: Hank Preston
Author-email: hank.preston@gmail.com
License: MIT license
Keywords: webexteamsbot
Platform: UNKNOWN
Classifier: Development Status :: 2 - Pre-Alpha
Classifier: Intended Audience :: Developers
Classifier: License :: OSI Approved :: MIT License
Classifier: Natural Language :: English
Classifier: Programming Language :: Python :: 2
Classifier: Programming Language :: Python :: 2.7
Classifier: Programming Language :: Python :: 3
Classifier: Programming Language :: Python :: 3.4
Classifier: Programming Language :: Python :: 3.5
Classifier: Programming Language :: Python :: 3.6
Classifier: Programming Language :: Python :: 3.7
